scBiMapping/__init__.py
scBiMapping/scBiMapping.py
scBiMapping-1.0.0.dist-info/LICENSE.txt
scBiMapping-1.0.0.dist-info/METADATA
scBiMapping-1.0.0.dist-info/WHEEL
scBiMapping-1.0.0.dist-info/top_level.txt
scBiMapping-1.0.0.dist-info/RECORD
