Metadata-Version: 2.1
Name: scBiMapping
Version: 1.0.0
Summary: non-linear dimension reduction
Author: Qiu Teng
License-File: LICENSE.txt
